Metadata-Version: 2.1
Name: py-wind
Version: 0.0.7.1
Summary: Python Wind api
Home-page: https://github.com/haifengat/py_wind
Author: HaiFeng
Author-email: haifengat@vip.qq.com
License: MIT License
Platform: any
Classifier: Programming Language :: Python :: 3
Classifier: Programming Language :: Python :: 3.4
Classifier: Programming Language :: Python :: 3.5
Classifier: Programming Language :: Python :: 3.6
Classifier: Programming Language :: Python :: 3.7
Classifier: License :: OSI Approved :: MIT License
Classifier: Operating System :: OS Independent
Requires-Python: >=3.6.0
